Metadata-Version: 1.0
Name: raptus.article.person
Version: 0.1
Summary: Provides a new contenttype person with view and portlet
Home-page: http://svn.plone.org/svn/collective/
Author: Claudio Marangon
Author-email: dev@raptus.com
License: gpl
Platform: UNKNOWN
Classifier: Programming Language :: Python
